{
  "teacher_name": "openclip_l14_dfn2b",
  "model_tag": "openclip::ViT-L-14::dfn2b",
  "teacher_meta": {
    "model_family": "openclip",
    "model_name": "ViT-L-14",
    "pretrained": "dfn2b",
    "prompt_class_names": [
      "bird",
      "bobcat",
      "cat",
      "coyote",
      "dog",
      "empty",
      "opossum",
      "rabbit",
      "raccoon",
      "squirrel"
    ],
    "prompt_templates": [
      "a photo of a {}.",
      "a photo of the {}.",
      "a picture of a {}.",
      "a picture of the {}.",
      "an image of a {}.",
      "an image of the {}.",
      "a cropped photo of a {}.",
      "a close-up photo of a {}.",
      "a clean photo of a {}.",
      "a bright photo of a {}.",
      "a good photo of a {}.",
      "a centered photo of a {}.",
      "a studio photo of a {}.",
      "a product photo of a {}."
    ],
    "logit_scale": 14.284856796264648,
    "teacher_family_group": "dfn"
  },
  "probe": {
    "type": "LogisticRegression",
    "standardize_features": true,
    "C": 1.0,
    "max_iter": 2000,
    "test_size": 0.2,
    "random_state": 42
  },
  "train_domain": "location_38",
  "domains": {
    "location_38": {
      "split": "heldout_20_percent",
      "accuracy": 0.8572159672466735,
      "balanced_accuracy": 0.7050206736939983,
      "n_samples": 1954
    },
    "location_100": {
      "split": "full_domain_ood",
      "accuracy": 0.44127895060463207,
      "balanced_accuracy": 0.34689170581743667,
      "n_samples": 4879
    },
    "location_43": {
      "split": "full_domain_ood",
      "accuracy": 0.1582089552238806,
      "balanced_accuracy": 0.19871356733111709,
      "n_samples": 4020
    },
    "location_46": {
      "split": "full_domain_ood",
      "accuracy": 0.231296961777197,
      "balanced_accuracy": 0.22460540679664937,
      "n_samples": 6122
    }
  }
}